Metadata-Version: 2.1
Name: overloaded-iterables
Version: 0.7.34
Summary: Overloaded version of the built-in python classes: list and set, to include some extra functionalities.
Home-page: https://github.com/Arkiralor/overloaded_iterables
Author: Prithoo Medhi
Author-email: prithoo11335@gmail.com
License: MIT
Keywords: python,built-in overloading,sequence,overloading,median,rms,root-mean-square,mean,sort,graph,histogram,scatterplot,line-plot,queue,stack
Platform: windows
Platform: ubuntu-linux
Platform: mac-os
Classifier: Development Status :: 3 - Alpha
Classifier: Topic :: Utilities
Classifier: License :: OSI Approved :: MIT License
License-File: LICENSE
